LICENSE
README.md
setup.cfg
setup.py
aiopayAPI/__init__.py
aiopayAPI/config.py
aiopayAPI/exceptions.py
aiopayAPI/payok.py
aiopayAPI/quick.py
aiopayAPI/urls.py
aiopayAPI.egg-info/PKG-INFO
aiopayAPI.egg-info/SOURCES.txt
aiopayAPI.egg-info/dependency_links.txt
aiopayAPI.egg-info/requires.txt
aiopayAPI.egg-info/top_level.txt
aiopayAPI/types/__init__.py
aiopayAPI/types/commissions.py
aiopayAPI/types/methods.py
aiopayAPI/utils/__init__.py
aiopayAPI/utils/check.py
aiopayAPI/utils/operations.py