Metadata-Version: 2.1
Name: aiopayAPI
Version: 0.1.5.1
Summary: Асинхронный API для работы с платежной системой Payok.io.
Home-page: https://github.com/artizsq/aiopayAPI
Author: artiz.sq
Author-email: 090504opo@gmail.com
Keywords: python PayOk payok api API asyncio payok оплата платежи
Classifier: Programming Language :: Python :: 3.8
Classifier: Programming Language :: Python :: 3.9
Classifier: Programming Language :: Python :: 3.10
Classifier: Programming Language :: Python :: 3.11
Classifier: License :: OSI Approved :: MIT License
Classifier: Operating System :: OS Independent
Requires-Python: >=3.8
License-File: LICENSE
